simpleboto/__init__.py
simpleboto/boto3_base.py
simpleboto/athena/__init__.py
simpleboto/athena/athena_client.py
simpleboto/athena/constants/__init__.py
simpleboto/athena/constants/constants.py
simpleboto/athena/sql/create_table.sql
simpleboto/athena/utils/__init__.py
simpleboto/athena/utils/data_types.py
simpleboto/athena/utils/schema.py
simpleboto/exceptions/__init__.py
simpleboto/exceptions/custom_exceptions.py
simpleboto/logs/__init__.py
simpleboto/logs/logger.py
simpleboto/s3/__init__.py
simpleboto/s3/s3_client.py
simpleboto/s3/s3_url.py
simpleboto/utils/__init__.py
simpleboto/utils/functions.py
simpleboto-0.4.4.dist-info/LICENSE.txt
simpleboto-0.4.4.dist-info/METADATA
simpleboto-0.4.4.dist-info/WHEEL
simpleboto-0.4.4.dist-info/top_level.txt
simpleboto-0.4.4.dist-info/RECORD
