Metadata-Version: 2.1
Name: simpleboto
Version: 0.4.4
Summary: A tool for easier use of boto3 methods
Home-page: https://github.com/ccollier97/simpleboto/
Author: Charlie Collier
License-File: LICENSE.txt
Requires-Dist: setuptools >=60.0.0
Requires-Dist: wheel >=0.37.0
Requires-Dist: boto3
